idlmagic/__init__.py
idlmagic/__version__.py
idlmagic/idlmagic.py
idlmagic-0.1.0.dist-info/METADATA
idlmagic-0.1.0.dist-info/RECORD
idlmagic-0.1.0.dist-info/WHEEL
idlmagic-0.1.0.dist-info/top_level.txt
