Metadata-Version: 2.1
Name: idlmagic
Version: 0.1.0
Summary: %%idl magic for IPython and Jupyter notebooks, providing access to Harris Geospatial's IDL programming language.
Home-page: https://github.com/r4lv/ipython-idl-magic
Author: r4lv
Author-email: r4lv@peaxels.com
License: MIT
Platform: UNKNOWN
Classifier: License :: OSI Approved :: MIT License
Classifier: Operating System :: OS Independent
Classifier: Programming Language :: Python
Classifier: Programming Language :: Python :: 3
Classifier: Programming Language :: Other
Classifier: Framework :: IPython
Classifier: Framework :: Jupyter
Classifier: Intended Audience :: Science/Research
Classifier: Topic :: Scientific/Engineering :: Physics
Classifier: Topic :: Scientific/Engineering :: Astronomy
Classifier: Topic :: Software Development :: Libraries
Requires-Python: >=3.0.0
Requires-Dist: IPython
